RPiMCP23S17/MCP23S17.py
RPiMCP23S17/__init__.py
RPiMCP23S17-1.0.0.dist-info/COPYING.txt
RPiMCP23S17-1.0.0.dist-info/METADATA
RPiMCP23S17-1.0.0.dist-info/WHEEL
RPiMCP23S17-1.0.0.dist-info/top_level.txt
RPiMCP23S17-1.0.0.dist-info/RECORD
