Metadata-Version: 2.1
Name: RPiMCP23S17
Version: 1.0.0
Summary: A module to access GPIO expanders MCP23S17 from a Raspberry Pi.
Home-page: http://github.com/petrockblog/RPi-MCP23S17
Author: Florian Mueller
Author-email: contact@petrockblock.com
License: MIT
Keywords: Raspberry Pi GPIO MCP23S17 SPI
Platform: UNKNOWN
Classifier: Development Status :: 5 - Production/Stable
Classifier: Operating System :: POSIX :: Linux
Classifier: License :: OSI Approved :: MIT License
Classifier: Intended Audience :: Developers
Classifier: Programming Language :: Python :: 2.6
Classifier: Programming Language :: Python :: 2.7
Classifier: Programming Language :: Python :: 3
Classifier: Topic :: Software Development
Classifier: Topic :: Home Automation
Classifier: Topic :: System :: Hardware
Requires-Dist: RPi.GPIO
Requires-Dist: spidev
